{
  "song_title": "ハルカ",
  "artist_name": "YOASOBI",
  "confidence_score": 0.99,
  "search_queries_used": [
    "ハルカ YOASOBI 歌詞"
  ],
  "reasoning": "The lyrics were retrieved from two reliable Japanese lyrics websites (uta-net.com and utaten.com), both of which contain identical content that matches the provided ASR transcript. The lyrics on these sites are complete and match the vocal transcription perfectly, including the opening lines '思い出すのは出会った日のこと' and closing lines 'ご視聴ありがとうございました'. Cross-verification between two authoritative sources confirms accuracy.",
  "lyrics_content": "思い出すのは\n出会った日のこと\n誰の元にも帰れないボクを\n見つけ出してくれた\n救い出してくれた\n忘れることない君の笑顔\n暮らしのすきま\nよふけの祈り\nいつでも君と共に歩いてきたキセキ\nつらいことも\nうれしいことも\n分かち合えるそんな\n日々よ\nふりかえれば数え切れない\n思い出があふれ出してくる\nだれにも見えないところで\nがんばってる\n君のそばにいられること\nそれだけで\nこんなにほら幸せなんだよ\nこみ上げてくる\n想いはただ\nありがとう\n訪れた\nよろこびの春は\n旅立ちの季節\nはなれた街にも\n連れ出してくれたね\nひとり不安な日々に\nさみしそうな君に\n送るエール\nボクがついてるよ\n楽しいことばかりじゃない日常に\nあふれだした君の涙\nそれでも\n前を向いて歩いて\nそうやって大人になってく\n君のそばにいられること\n君のよろこびは\nボクのよろこびで\n君の大切が幸せが\nいつまでも君とありますように\nねえ\n君のそばにはもう\nたくさんの愛があふれてる\nだから今は\nどうか泣かないで\nあの日のように笑顔で\nふりかえればいくつもの\n思い出がよみがえってくる\nだれにも見えないところで\n流した涙もほら\n今の君につながってる\nたくさんの愛につながってる\nこみ上げてくる\n想いはただ\nありがとう\nいつまでも\n幸せで\nいつまでも\n愛してるよ",
  "lyrics_source_url": "https://www.uta-net.com/song/295523/",
  "native_language": "Japanese"
}